auditing/__init__.py
auditing/admin.py
auditing/apps.py
auditing/middleware.py
auditing/models.py
auditing/tests.py
auditing/utils.py
auditing/views.py
auditing/migrations/__init__.py
django_audit_wazuh-0.7.0.dist-info/LICENSE
django_audit_wazuh-0.7.0.dist-info/METADATA
django_audit_wazuh-0.7.0.dist-info/WHEEL
django_audit_wazuh-0.7.0.dist-info/top_level.txt
django_audit_wazuh-0.7.0.dist-info/RECORD
