Metadata-Version: 2.1
Name: django-audit-wazuh
Version: 0.7.0
Summary: Django Audit
Home-page: https://github.com/peppelinux/django-audit
Author: Giuseppe De Marco
Author-email: giuseppe.demarco@unical.it
License: Apache
Platform: UNKNOWN
Classifier: Environment :: Web Environment
Classifier: Framework :: Django
Classifier: Framework :: Django :: 3.0
Classifier: Framework :: Django :: 3.1
Classifier: Framework :: Django :: 3.2
Classifier: Intended Audience :: Developers
Classifier: License :: OSI Approved :: Apache Software License
Classifier: Operating System :: OS Independent
Classifier: Programming Language :: Python :: 3
Requires-Dist: django (<4.0,>=3.0)
